odoo/addons/product_packaging_type_vendor/README.rst
odoo/addons/product_packaging_type_vendor/__init__.py
odoo/addons/product_packaging_type_vendor/__manifest__.py
odoo/addons/product_packaging_type_vendor/i18n/it.po
odoo/addons/product_packaging_type_vendor/i18n/product_packaging_type_vendor.pot
odoo/addons/product_packaging_type_vendor/models/__init__.py
odoo/addons/product_packaging_type_vendor/models/product_packaging_type.py
odoo/addons/product_packaging_type_vendor/readme/CONTRIBUTORS.rst
odoo/addons/product_packaging_type_vendor/readme/DESCRIPTION.rst
odoo/addons/product_packaging_type_vendor/static/description/icon.png
odoo/addons/product_packaging_type_vendor/static/description/index.html
odoo/addons/product_packaging_type_vendor/views/product_packaging_type_view.xml
odoo14_addon_product_packaging_type_vendor-14.0.1.0.1.dev5.dist-info/METADATA
odoo14_addon_product_packaging_type_vendor-14.0.1.0.1.dev5.dist-info/WHEEL
odoo14_addon_product_packaging_type_vendor-14.0.1.0.1.dev5.dist-info/top_level.txt
odoo14_addon_product_packaging_type_vendor-14.0.1.0.1.dev5.dist-info/RECORD
